codeas/__init__.py
codeas/main.py
codeas/configs/agents_configs.py
codeas/configs/llm_params.py
codeas/configs/prompts.py
codeas/core/agent.py
codeas/core/clients.py
codeas/core/llm.py
codeas/core/metadata.py
codeas/core/repo.py
codeas/core/retriever.py
codeas/core/state.py
codeas/core/usage_tracker.py
codeas/ui/ui_state.py
codeas/ui/utils.py
codeas/ui/🏠_Home.py
codeas/ui/components/__init__.py
codeas/ui/components/deployment_ui.py
codeas/ui/components/documentation_ui.py
codeas/ui/components/metadata_ui.py
codeas/ui/components/page_ui.py
codeas/ui/components/refactoring_ui.py
codeas/ui/components/repo_ui.py
codeas/ui/components/testing_ui.py
codeas/ui/pages/1_📚_Documentation.py
codeas/ui/pages/2_🚀_Deployment.py
codeas/ui/pages/3_🧪_Testing.py
codeas/ui/pages/4_🔄_Refactoring.py
codeas/ui/pages/5_💬_Chat.py
codeas/ui/pages/6_📝_Prompts.py
codeas/ui/pages/7_🔍_Usage.py
codeas/use_cases/deployment.py
codeas/use_cases/documentation.py
codeas/use_cases/refactoring.py
codeas/use_cases/testing.py
codeas-0.4.1.dist-info/LICENSE
codeas-0.4.1.dist-info/METADATA
codeas-0.4.1.dist-info/WHEEL
codeas-0.4.1.dist-info/entry_points.txt
codeas-0.4.1.dist-info/top_level.txt
codeas-0.4.1.dist-info/RECORD
