Metadata-Version: 2.1
Name: codeas
Version: 0.4.1
Summary: Boost your software development processes with generative AI.
Author-email: Manuel Renner <manuel.renner@diverger.ai>, Diverger Thinking <info@diverger.ai>
License: MIT License
Project-URL: Source, https://github.com/DivergerThinking/codeas
Project-URL: Homepage, https://diverger.ai
Requires-Python: <3.12,>=3.9
License-File: LICENSE
Requires-Dist: openai >=1.51.0
Requires-Dist: pydantic >=2.5.0
Requires-Dist: python-dotenv >=1.0.0
Requires-Dist: streamlit >=1.28.0
Requires-Dist: pandas >=2.1.0
Requires-Dist: tokencost >=0.1.12
Requires-Dist: streamlit-nested-layout >=0.1.0
Requires-Dist: tenacity >=8.2.2
Requires-Dist: diff-match-patch >=20230430
Requires-Dist: google-generativeai >=0.8.3
Requires-Dist: anthropic >=0.36.1
